floweaver_path/__init__.py
floweaver_path/visualizer.py
floweaver_path/lib/__init__.py
floweaver_path/lib/ts_sankey.py
floweaver_path/lib/utils.py
floweaver_path-0.0.3.dist-info/LICENSE
floweaver_path-0.0.3.dist-info/METADATA
floweaver_path-0.0.3.dist-info/WHEEL
floweaver_path-0.0.3.dist-info/top_level.txt
floweaver_path-0.0.3.dist-info/RECORD
