Metadata-Version: 2.1
Name: floweaver-path
Version: 0.0.3
Summary: floweaver extension to handle the path visualization
Home-page: https://github.com/fullflu/floweaver-path
Author: fullflu
Author-email: k.takayama0902@gmail.com
License: MIT
Keywords: floweaver-path
Platform: UNKNOWN
Classifier: License :: OSI Approved :: MIT License
Classifier: Programming Language :: Python :: 3.6
Requires-Dist: floweaver
Requires-Dist: ipysankeywidget
